[
  {
    "category": "🏆 Sports Channels",
    "channels": [
      {
        "name": "T-Sports (Server 1)",
        "logo": "https://raw.githubusercontent.com/subirkumarpaul/Logo/main/T%20Sports.png",
        "url": "http://10.251.251.2:7171/t-sports/index.m3u8"
      },
      {
        "name": "T-Sports (Server 2)",
        "logo": "https://raw.githubusercontent.com/subirkumarpaul/Logo/main/T%20Sports.png",
        "url": "http://10.251.251.2:7171/beinsport2/index.m3u8"
      },
      {
        "name": "WIN Sports {FIFA}",
        "logo": "https://i.ibb.co.com/FbNGKKb9/win.jpg",
        "url": "https://1nyaler.streamhostingcdn.top/stream/32/index.m3u8"
      },
      {
        "name": "Bein Sports 1 {FIFA}",
        "logo": "https://i.ibb.co.com/cXQWGjyb/Bein-Sports-1.jpg",
        "url": "https://1nyaler.streamhostingcdn.top/stream/23/index.m3u8"
      },
      {
        "name": "DD Sports",
        "logo": "https://i.ibb.co.com/VchBJ37W/DD-Sports.png",
        "url": "https://d3qs3d2rkhfqrt.cloudfront.net/out/v1/b17adfe543354fdd8d189b110617cddd/index.m3u8"
      },
      {
        "name": "Sony Ten Cricket HD",
        "logo": "https://assets-prod.services.toffeelive.com/f_png,w_300,q_85/ra2x_pQBrjBfS2_RWG9l/posters/795170c2-ec78-457e-9fa0-54a23d23361c.webp",
        "url": "https://d3qs3d2rkhfqrt.cloudfront.net/out/v1/b17adfe543354fdd8d189b110617cddd/index.m3u8"
      },
      {
        "name": "Bleav Football",
        "logo": "https://s3.aynaott.com/storage/030ec528e912afb9a2ec3b4c5167a928",
        "url": "https://linear-493.frequency.stream/dist/glewedtv/493/hls/master/playlist.m3u8"
      },
      {
        "name": "DD Sports (Alt)",
        "logo": "https://s3.aynaott.com/storage/188500190395c4de0e506d518925dcc4",
        "url": "https://cdn-6.pishow.tv/live/13/master.m3u8"
      },
      {
        "name": "Bahrain Sports",
        "logo": "https://s3.aynaott.com/storage/f55bea3263be1af187fe1122e4f44142",
        "url": "https://5c7b683162943.streamlock.net/live/ngrp:sportsone_all/playlist.m3u8"
      },
      {
        "name": "Sports Fishing TV",
        "logo": "https://ui-avatars.com/api/?name=Fishing&background=2a2d35&color=fff&rounded=true",
        "url": "https://streams2.sofast.tv/v1/master/611d79b11b77e2f571934fd80ca1413453772ac7/eea68b79-bfe2-451e-a227-d637a5b9548a/manifest.m3u8"
      }
    ]
  },
  {
    "category": "🍿 Bangla Channels",
    "channels": [
      {
        "name": "Rajdhani TV",
        "logo": "https://i.ibb.co.com/21cf2JMJ/raj.jpg",
        "url": "https://stream.shariarsuvo.com/hls5/rajdhanicable.m3u8"
      },
      {
        "name": "Ayna",
        "logo": "https://i.ibb.co.com/F4QWxMQ1/ayna.jpg",
        "url": "https://app24.jagobd.com.bd/c3VydmVyX8RpbEU9Mi8xNy8yMFDEEHGcfRgzQ6NTAgdEoaeFzbF92YWxIZTO0U0ezN1IzMyfvcEdsEfeDeKiNkVN3PTOmdFseWRtaW51aiPhnPTI2/ayna.stream/index.m3u8"
      },
      {
        "name": "Channel S BD",
        "logo": "https://i.ibb.co.com/nqgrD4VB/chsbd.jpgg",
        "url": "https://app24.jagobd.com.bd/c3VydmVyX8RpbEU9Mi8xNy8yMFDEEHGcfRgzQ6NTAgdEoaeFzbF92YWxIZTO0U0ezN1IzMyfvcEdsEfeDeKiNkVN3PTOmdFseWRtaW51aiPhnPTI2/channels.stream/index.m3u8"
      },
      {
        "name": "Desh TV",
        "logo": "https://i.ibb.co.com/hRfwD8jk/DESH-TV1.png",
        "url": "https://app24.jagobd.com.bd/c3VydmVyX8RpbEU9Mi8xNy8yMFDEEHGcfRgzQ6NTAgdEoaeFzbF92YWxIZTO0U0ezN1IzMyfvcEdsEfeDeKiNkVN3PTOmdFseWRtaW51aiPhnPTI2/deshtv.stream/index.m3u8"
      },
      {
        "name": "Ekushey TV",
        "logo": "https://i.ibb.co.com/JwWDTBpG/ekusheytv.jpg",
        "url": "https://app24.jagobd.com.bd/c3VydmVyX8RpbEU9Mi8xNy8yMFDEEHGcfRgzQ6NTAgdEoaeFzbF92YWxIZTO0U0ezN1IzMyfvcEdsEfeDeKiNkVN3PTOmdFseWRtaW51aiPhnPTI2/ekusheytv-8-org.stream/index.m3u8"
      },
      {
        "name": "Enter TV",
        "logo": "https://i.ibb.co.com/Ng4D11Vr/entertv.jpg",
        "url": "https://live1.entertv.com.bd/entertv/index.fmp4.m3u8"
      },
      {
        "name": "Global TV",
        "logo": "https://i.ibb.co.com/VW3CX9WS/globaltv.jpg",
        "url": "https://app24.jagobd.com.bd/c3VydmVyX8RpbEU9Mi8xNy8yMFDEEHGcfRgzQ6NTAgdEoaeFzbF92YWxIZTO0U0ezN1IzMyfvcEdsEfeDeKiNkVN3PTOmdFseWRtaW51aiPhnPTI2/Global-tv.stream/index.m3u8"
      },
      {
        "name": "Jagonews24",
        "logo": "https://i.ibb.co.com/C3Y8NtQz/jagonews24.png",
        "url": "https://app.ncare.live/live-orgin/jagonews24.stream/playlist.m3u8"
      },
      {
        "name": "Mohona TV",
        "logo": "https://i.ibb.co.com/Z6yn2N5v/mohona.jpg",
        "url": "https://app24.jagobd.com.bd/c3VydmVyX8RpbEU9Mi8xNy8yMFDEEHGcfRgzQ6NTAgdEoaeFzbF92YWxIZTO0U0ezN1IzMyfvcEdsEfeDeKiNkVN3PTOmdFseWRtaW51aiPhnPTI2/mohonatv.stream/index.m3u8"
      },
      {
        "name": "RTV",
        "logo": "https://app24.jagobd.com.bd/c3VydmVyX8RpbEU9Mi8xNy8yMFDEEHGcfRgzQ6NTAgdEoaeFzbF92YWxIZTO0U0ezN1IzMyfvcEdsEfeDeKiNkVN3PTOmdFseWRtaW51aiPhnPTI2/rtv-sg.stream/index.m3u8",
        "url": "https://app24.jagobd.com.bd/c3VydmVyX8RpbEU9Mi8xNy8yMFDEEHGcfRgzQ6NTAgdEoaeFzbF92YWxIZTO0U0ezN1IzMyfvcEdsEfeDeKiNkVN3PTOmdFseWRtaW51aiPhnPTI2/rtv-sg.stream/index.m3u8"
      },
      {
        "name": "Thikana TV",
        "logo": "https://i.ibb.co.com/RpwqzPZg/thikana.png",
        "url": "https://app24.jagobd.com.bd/c3VydmVyX8RpbEU9Mi8xNy8yMFDEEHGcfRgzQ6NTAgdEoaeFzbF92YWxIZTO0U0ezN1IzMyfvcEdsEfeDeKiNkVN3PTOmdFseWRtaW51aiPhnPTI2/thikanatv.stream/index.m3u8"
      },
      {
        "name": "Toffee Dramas",
        "logo": "https://i.ibb.co.com/xt6RK79j/toffeed.png",
        "url": "https://ottbanglaplatform.com/tv/toffee/live.php?id=toffee_drama&e=.m3u8"
      }
    ]
  },
  {
    "category": "🍿 Bangla Entertainment",
    "channels": [
      {
        "name": "Star Jalsha",
        "logo": "https://raw.githubusercontent.com/Rakib49/Rakibiptv/main/images%20(9).jpeg",
        "url": "https://yupptvcatchupire.yuppcdn.net/preview/starjalsha/1800.m3u8"
      },
      {
        "name": "Zee Bangla HD",
        "logo": "https://raw.githubusercontent.com/subirkumarpaul/Logo/main/zee%20Bangla.png",
        "url": "https://cdn-4.pishow.tv/live/1143/master.m3u8"
      },
      {
        "name": "ZEE BANGLA",
        "logo": "https://tvassets.roarzone.net/images/34.png",
        "url": "https://yupptvcatchupire.yuppcdn.net/preview/zeebangla/2500.m3u8"
      },
      {
        "name": "Colors Bangla",
        "logo": "https://dl.dropbox.com/s/44vdhjj6fja02co/CBHD.jpg",
        "url": "https://yupptvcatchupire.yuppcdn.net/preview/colorsbanglahd/800.m3u8"
      },
      {
        "name": "Deepto TV",
        "logo": "https://upload.wikimedia.org/wikipedia/en/3/31/Deepto_TV_logo.png",
        "url": "https://byphdgllyk.gpcdn.net/hls/deeptotv/0_1/index.m3u8"
      },
      {
        "name": "Thikana",
        "logo": "https://s3.aynaott.com/storage/6d1aaa03b84a69992940873fc11af8fc",
        "url": "https://5dd3981940faa.streamlock.net:443/thikanatv/thikanatv/playlist.m3u8"
      },
      {
        "name": "DD Bangla",
        "logo": "https://s3.aynaott.com/storage/e5117c508d18adf0a3f2475eb1fd5a9d",
        "url": "https://d3qs3d2rkhfqrt.cloudfront.net/out/v1/7ff57cc9046b4c188b51a0d506f36e7f/index_3.m3u8"
      },
      {
        "name": "Enter 10 Bangla",
        "logo": "https://s3.aynaott.com/storage/2b00567c538d392c8050124f0064c4a1",
        "url": "https://live-bangla.akamaized.net/liveabr/playlist.m3u8"
      },
      {
        "name": "Deshe Bideshe",
        "logo": "https://pbs.twimg.com/profile_images/739539785304281088/zMwNO936_400x400.jpg",
        "url": "https://dbcanada.sonarbanglatv.com/deshebideshe/dbtv/index.m3u8"
      }
    ]
  },
  {
    "category": "🌐 Hindi Channels",
    "channels": [
      {
        "name": "AAJ Entertainment",
        "logo": "https://i.ibb.co.com/fGFV4nB0/aaj-entertainment.png",
        "url": "https://ml-pull-dvc-myco.io:2096/AAJ_ENTERTAINMENT/index.m3u8"
      },
      {
        "name": "GEO Entertainment",
        "logo": "https://i.ibb.co.com/wV9f2FR/Geo-Entertainment.png",
        "url": "https://ml-pull-dvc-myco.io:2096/GEO_ENTERTAINEMNT/index.m3u8"
      },
      {
        "name": "Green Entertainment",
        "logo": "https://i.ibb.co.com/fGx2j20K/Green-Entertainment.jpg",
        "url": "https://ml-pull-dvc-myco.io:2096/GREEN_ENTERTAINMENT/index.m3u8"
      },
      {
        "name": "Hum TV",
        "logo": "https://i.ibb.co.com/jkkPqjQY/Hum-TV.png",
        "url": "https://ml-pull-dvc-myco.io:2096/HUM_ENTERTAINMENT/index.m3u8"
      },
      {
        "name": "R Plus News",
        "logo": "https://i.ibb.co.com/HfJv8ddj/r-plus-news.jpg",
        "url": "https://thelegitpro.in/pntv/rplusnews24x7/index.m3u8"
      }
    ]
  },
  {
    "category": "📰 Live News & Info",
    "channels": [
      {
        "name": "TV9 Bangla",
        "logo": "https://s3.aynaott.com/storage/7b93f6be496c9fd25769b09970180c4c",
        "url": "https://dyjmyiv3bp2ez.cloudfront.net/pub-iotv9banaen8yq/liveabr/playlist.m3u8"
      },
      {
        "name": "AlJazeera",
        "logo": "https://s3.aynaott.com/storage/5d707a103f48d8f9f1634f1b70e2ecdf",
        "url": "https://live-hls-apps-aje-fa.getaj.net/AJE/index.m3u8"
      },
      {
        "name": "DW News",
        "logo": "https://s3.aynaott.com/storage/0ce159bdea29fce7e3e85d12bc8a10c5",
        "url": "https://dwamdstream102.akamaized.net/hls/live/2015525/dwstream102/master.m3u8"
      },
      {
        "name": "Wion",
        "logo": "https://s3.aynaott.com/storage/671cfb22f8d0362ae01403b6e748f2e2",
        "url": "https://d7x8z4yuq42qn.cloudfront.net/index_7.m3u8"
      },
      {
        "name": "TRT World",
        "logo": "https://s3.aynaott.com/storage/f63d4aad95532175f7f44be439f74111",
        "url": "https://tv-trtworld.medya.trt.com.tr/master.m3u8"
      },
      {
        "name": "News Nation",
        "logo": "https://s3.aynaott.com/storage/1001f1d96d63da3ced733a843613b6e0",
        "url": "https://d3qs3d2rkhfqrt.cloudfront.net/out/v1/6cd2f649739a45ca9de1daf81cc7d0f2/index.m3u8"
      },
      {
        "name": "India Today",
        "logo": "https://s3.aynaott.com/storage/49b496bca6d7c67d53431e9238f83397",
        "url": "https://feeds.intoday.in/hltapps/api/master.m3u8"
      },
      {
        "name": "OAN",
        "logo": "https://s3.aynaott.com/storage/73820738ff3902737f987eb34612b26d",
        "url": "https://a-cdn.klowdtv.com/live1/oan_720p/playlist.m3u8"
      },
      {
        "name": "Iran Press",
        "logo": "https://s3.aynaott.com/storage/201491b7327fffb27d78f800dd9f42d2",
        "url": "https://live.presstv.ir/hls/presstv_5_482/index.m3u8"
      },
      {
        "name": "R Plus News (Alt)",
        "logo": "https://s3.aynaott.com/storage/9531f970bb7abf30ac2a48f40838c3a1",
        "url": "https://thelegitpro.in/pntv/rplusnews24x7/index.m3u8"
      },
      {
        "name": "BEK TV News",
        "logo": "https://s3.aynaott.com/storage/4eaf83274ee309489b535852b1780ad2",
        "url": "https://cdn3.wowza.com/5/ZWQ1K2NYTmpFbGsr/BEK-WOWZA-1/smil:BEKPRIMEeast.smil/playlist.m3u8"
      }
    ]
  },
  {
    "category": "🔬 Infotainment",
    "channels": [
      {
        "name": "Discovery HD",
        "logo": "https://raw.githubusercontent.com/subirkumarpaul/Logo/main/Discovery%20.png",
        "url": "https://wildearth-plex.amagi.tv/master.m3u8"
      },
      {
        "name": "Animal Planet HD",
        "logo": "https://raw.githubusercontent.com/subirkumarpaul/Logo/main/Animal%20Planet.png",
        "url": "https://tiger-hub.vercel.app@vodzong.mjunoon.tv:8087/streamtest/Animal-Planet-158-3/playlist.m3u8"
      },
      {
        "name": "Sony BBC Earth HD",
        "logo": "https://raw.githubusercontent.com/subirkumarpaul/Logo/main/Sony%20BBC%20Earth.jpeg",
        "url": "https://wildearth-plex.amagi.tv/master.m3u8"
      },
      {
        "name": "History TV 18 HD",
        "logo": "https://images.toffeelive.com/images/program/2429/logo/240x240/mobile_logo_009938001674474908.png",
        "url": "https://cdn1.logichost.in/ajmantv/live/playlist.m3u8"
      }
    ]
  },
  {
    "category": "🧸 Kids Channels",
    "channels": [
      {
        "name": "Cartoon Network HD (Server 2)",
        "logo": "https://raw.githubusercontent.com/subirkumarpaul/Logo/main/Cartoon%20Network.png",
        "url": "https://live20.bozztv.com/giatvplayout7/giatv-208314/playlist.m3u8"
      },
      {
        "name": "Nick Bangla",
        "logo": "https://raw.githubusercontent.com/subirkumarpaul/Logo/main/Nick.png",
        "url": "https://live20.bozztv.com/giatvplayout7/giatv-209902/tracks-v1a1/mono.ts.m3u8"
      },
      {
        "name": "Sony Yay",
        "logo": "https://raw.githubusercontent.com/subirkumarpaul/Logo/main/Sony%20Yay.png",
        "url": "https://cc-4bhi5osabejc9.akamaized.net/v1/master/3722c60a815c199d9c0ef36c5b73da68a62b09d1/cc-4bhi5osabejc9/junglebook.m3u8"
      },
      {
        "name": "Pogo",
        "logo": "https://raw.githubusercontent.com/subirkumarpaul/Logo/main/POGO.jpeg",
        "url": "https://live20.bozztv.com/giatvplayout7/giatv-209622/tracks-v1a1/mono.ts.m3u8"
      },
      {
        "name": "Jungle Book",
        "logo": "https://i.imgur.com/ubZMeQv.jpg",
        "url": "https://cc-4bhi5osabejc9.akamaized.net/v1/master/3722c60a815c199d9c0ef36c5b73da68a62b09d1/cc-4bhi5osabejc9/junglebook.m3u8"
      },
      {
        "name": "Rongeen TV",
        "logo": "https://i.postimg.cc/zBCLNtGZ/Duronto.jpg",
        "url": "https://server.thelegitpro.in/rongeentv/rongeentv/tracks-v1a1/mono.m3u8"
      },
      {
        "name": "Dios Te Ve Kids",
        "logo": "https://s3.aynaott.com/storage/6712a3c8a28689cfda4148faf095fa67",
        "url": "https://s.emisoras.tv:8081/diostevekids/index.m3u8"
      },
      {
        "name": "TVCARiB Kids",
        "logo": "https://s3.aynaott.com/storage/c6fde511a99e5134dbf12b77da386cb6",
        "url": "https://cdn.mycloudstream.io/hls/live/broadcast/nro19k2h/index.m3u8"
      }
    ]
  },
  {
    "category": "🎬 Movies, Music & Doc",
    "channels": [
      {
        "name": "Sangeet Bangla",
        "logo": "https://s3.aynaott.com/storage/80424ce0682e14e7d51e28de33d5f380",
        "url": "https://cdn-4.pishow.tv/live/1143/master.m3u8"
      },
      {
        "name": "SRK TV",
        "logo": "https://raw.githubusercontent.com/Rakib49/Rakibiptv/main/IMG_20260528_193117_215.jpg",
        "url": "https://srknowapp.ncare.live/srktvhlswodrm/srktv.stream/playlist.m3u8"
      },
      {
        "name": "G Series Drama",
        "logo": "https://raw.githubusercontent.com/Rakib49/Rakibiptv/main/images%20(7).jpeg",
        "url": "https://vods2.aynaott.com/gseriesDrama/tracks-v1a1/mono.ts.m3u8"
      },
      {
        "name": "ShemarooTV",
        "logo": "https://s3.aynaott.com/storage/c63628e7301ba1eded68c0f75ab8d903",
        "url": "https://cdn-3.pishow.tv/live/230/master.m3u8"
      },
      {
        "name": "Hindi Movie Clsc",
        "logo": "https://s3.aynaott.com/storage/3132515182ec50091b496fe515564084",
        "url": "https://vods2.aynaott.com/hindimovies/index.m3u8"
      },
      {
        "name": "TBS",
        "logo": "https://cdntv.tbs.seoul.kr/tbs/tbs_tv_web.smil/playlist.m3u8",
        "url": "https://cdntv.tbs.seoul.kr/tbs/tbs_tv_web.smil/playlist.m3u8"
      },
      {
        "name": "MovieSphere",
        "logo": "https://s3.aynaott.com/storage/4d343b446b1e7164bb7239bbe822a570",
        "url": "https://moviesphereuk-samsunguk.amagi.tv/playlist.m3u8"
      },
      {
        "name": "Rakuten Movies",
        "logo": "https://s3.aynaott.com/storage/22af43810a37af9a151f1e0a23adde63",
        "url": "https://0145451975a64b35866170fd2e8fa486.mediatailor.eu-west-1.amazonaws.com/v1/master/0547f18649bd788bec7b67b746e47670f558b6b2/production-LiveChannel-5987/master.m3u8"
      },
      {
        "name": "World War TV",
        "logo": "https://s3.aynaott.com/storage/1e7dc35fdb26ce3aca17b41fae1aa56f",
        "url": "https://aenetworks-worldwartv-rakuten.amagi.tv/playlist.m3u8"
      },
      {
        "name": "Cowboy Movie",
        "logo": "https://s3.aynaott.com/storage/cb1ab052f5b733bbf600a7a8e3a1164b",
        "url": "https://streams2.sofast.tv/sofastplayout/32eb332e-f644-46e5-ad91-e55ad80d14f7_0_HLS/master.m3u8"
      },
      {
        "name": "Persiana Kore",
        "logo": "https://s3.aynaott.com/storage/f24e50516ccf6b3e94a4ca749ccb3533",
        "url": "https://korhls.persiana.live/hls/stream.m3u8"
      },
      {
        "name": "Power Turk",
        "logo": "https://s3.aynaott.com/storage/c4f27e64c99b50629e7021b99ac9387a",
        "url": "https://livetv.powerapp.com.tr/powerturkTV/powerturkhd.smil/playlist.m3u8"
      },
      {
        "name": "Adven. Earth",
        "logo": "https://s3.aynaott.com/storage/13c04e44967d653c70eac9670b47fa5d",
        "url": "https://autentic-adventure-earth-1-eu.rakuten.wurl.tv/playlist.m3u8"
      },
      {
        "name": "Animal Planet",
        "logo": "https://s3.aynaott.com/storage/18d95033c5d53fc3b159141a842fdeac",
        "url": "https://tiger-hub.vercel.app@vodzong.mjunoon.tv:8087/streamtest/Animal-Planet-158-3/playlist.m3u8"
      }
    ]
  },
  {
    "category": "🌐 English & Hindi",
    "channels": [
      {
        "name": "Action H'wood",
        "logo": "https://s3.aynaott.com/storage/baef6dd41c3ee6fabbb59bb8403cc1eb",
        "url": "https://cdn-apse1-prod.tsv2.amagi.tv/linear/amg01076-lightningintern-actionhollywood-samsungnz/playlist.m3u8"
      },
      {
        "name": "Court TV",
        "logo": "https://s3.aynaott.com/storage/7deacf82c7f75cf7aaee5e0935c3d2c8",
        "url": "https://cdn-uw2-prod.tsv2.amagi.tv/linear/amg01438-ewscrippscompan-courttv-tablo/playlist.m3u8"
      },
      {
        "name": "Awaaz India",
        "logo": "https://s3.aynaott.com/storage/6f17785db48e7b5fb68b7d441ad3ad10",
        "url": "https://awaazindia.livebox.co.in/AwaazIndaTVhls/Live.m3u8"
      },
      {
        "name": "Music India",
        "logo": "https://s3.aynaott.com/storage/20c3a2638df99ece9eb12aabfc03a8c3",
        "url": "https://cdn-2.pishow.tv/live/226/master.m3u8"
      },
      {
        "name": "Khushboo",
        "logo": "https://s3.aynaott.com/storage/d90eb718a6674494d2dac28e1d96bf44",
        "url": "https://cdn-4.pishow.tv/live/1473/master.m3u8"
      }
    ]
  },
  {
    "category": "🗺️ Lifestyle & Travel",
    "channels": [
      {
        "name": "Travel XP",
        "logo": "https://s3.aynaott.com/storage/a676d2f5ddf6e5f978b3d51876dceecf",
        "url": "https://27c980761ff9437d929e64647afe183a.mediatailor.us-east-1.amazonaws.com/v1/master/44f73ba4d03e9607dcd9bebdcb8494d86964f1d8/RakutenTV-eu_TravelXP/playlist.m3u8"
      },
      {
        "name": "4k Travel TV",
        "logo": "https://s3.aynaott.com/storage/6ccc7357c3d8d35770732126dd819596",
        "url": "https://streams2.sofast.tv/sofastplayout/33c31ac4-51fa-46ae-afd0-0d1fe5e60a80_0_HLS/master.m3u8"
      },
      {
        "name": "InTravel",
        "logo": "https://s3.aynaott.com/storage/b35e9c1bcde3e6876892a22f91a9c4b5",
        "url": "https://amg00861-amg00861c10-rakuten-uk-3152.playouts.now.amagi.tv/playlist.m3u8"
      },
      {
        "name": "Wild TV",
        "logo": "https://s3.aynaott.com/storage/597c839e577e81813e44812cedc50892",
        "url": "https://dfhsahpa45kk2.cloudfront.net/scheduler/scheduleMaster/476.m3u8"
      }
    ]
  },
  {
    "category": "🕌 Religious, Weather & Info",
    "channels": [
      {
        "name": "Peace TV Bangla",
        "logo": "https://i.ibb.co/Gfw89mC/20240804-033102.png",
        "url": "https://dzkyvlfyge.erbvr.com/PeaceTvBangla/tracks-v2a1/mono.m3u8"
      },
      {
        "name": "Channel Win",
        "logo": "https://s3.aynaott.com/storage/3458d0d9097a8283a94a13374bcbf5c7",
        "url": "https://cdn-4.pishow.tv/live/229/master.m3u8"
      },
      {
        "name": "Discover PK",
        "logo": "https://s3.aynaott.com/storage/1b9208802bbf0cc01f1e8319b0ec633d",
        "url": "https://livecdn.live247stream.com/discoverpakistan/web/playlist.m3u8"
      },
      {
        "name": "Saudi Quran Live",
        "logo": "https://cdn-globecast.akamaized.net/live/eds/saudi_quran/logo.png",
        "url": "https://cdn-globecast.akamaized.net/live/eds/saudi_quran/hls_roku/index.m3u8"
      },
      {
        "name": "Makka Live",
        "logo": "https://s3.aynaott.com/storage/9b6f35f73a099b7a5885a970523c5f78",
        "url": "https://cdn-globecast.akamaized.net/live/eds/saudi_sunnah/hls_roku/index.m3u8"
      },
      {
        "name": "Saudia Radio",
        "logo": "https://s3.aynaott.com/storage/76d7d7446ee57ec14ff67c1678725d19",
        "url": "https://live.kwikmotion.com/sbrksasaudiaradiolive/srpksasaudiaradio/playlist.m3u8"
      },
      {
        "name": "ABN",
        "logo": "https://s3.aynaott.com/storage/9882913a8d68aa99c0501b64749d6320",
        "url": "https://mediaserver.abnvideos.com/streams/abnurdu.m3u8"
      },
      {
        "name": "AccuWeather",
        "logo": "https://s3.aynaott.com/storage/21992f5e8529a9d2a94b6edf917dbd8f",
        "url": "https://cdn-ue1-prod.tsv2.amagi.tv/linear/amg00684-accuweather-accuweather-plex/playlist.m3u8"
      },
      {
        "name": "Fox Weather",
        "logo": "https://s3.aynaott.com/storage/6dd20ecde19ea3f6b6cf6c040701973e",
        "url": "https://247wlive.foxweather.com/stream/index.m3u8"
      },
      {
        "name": "Sky Weather",
        "logo": "https://s3.aynaott.com/storage/78b7ab973209ec06346cf8acfd8544cd",
        "url": "https://distro001-gb-hls1-prd.delivery.skycdp.com/easel_cdn/ngrp:weather_loop.stream_all/playlist.m3u8"
      },
      {
        "name": "Weather SPY",
        "logo": "https://s3.aynaott.com/storage/b0bdea4df810e2d46f689cbb6c990c91",
        "url": "https://jukin-weatherspy-2-in.samsung.wurl.tv/playlist.m3u8"
      }
    ]
  }
]
